{
    "level": {
        "1": "5",
        "2": "12",
        "3": "22",
        "4": "35",
        "5": "51",
        "6": "70",
        "7": "92",
        "8": "117",
        "9": "145",
        "10": "176",
        "11": "210",
        "12": "247",
        "13": "287",
        "14": "330",
        "15": "376",
        "16": "425",
        "17": "477",
        "18": "532",
        "19": "590",
        "20": "651",
        "21": "715",
        "22": "782",
        "23": "852",
        "24": "925",
        "25": "1001",
        "26": "1080",
        "27": "1162",
        "28": "1227",
        "29": "1315",
        "30": "1406",
        "31": "1500",
        "32": "1597",
        "33": "1697",
        "34": "1800",
        "35": "1905",
        "36": "2010",
        "37": "2115",
        "38": "2220",
        "39": "2325",
        "40": "2430",
        "41": "2535",
        "42": "2640",
        "43": "2745",
        "44": "2850",
        "45": "2955",
        "46": "3060",
        "47": "3165",
        "48": "3270",
        "49": "3375",
        "50": "3480",
        "51": "3585",
        "52": "3690",
        "53": "3795",
        "54": "3900",
        "55": "4005",
        "56": "4110",
        "57": "4215",
        "58": "4320",
        "59": "4425",
        "60": "4530",
        "61": "4645",
        "62": "4760",
        "63": "4875",
        "64": "4990",
        "65": "5105",
        "66": "5220",
        "67": "5335",
        "68": "5450",
        "69": "5565",
        "70": "5680",
        "71": "5795",
        "72": "5910",
        "73": "6025",
        "74": "6140",
        "75": "6255",
        "76": "6370",
        "77": "6485",
        "78": "6600",
        "79": "6750",
        "80": "6900",
        "81": "7050",
        "82": "7200",
        "83": "7350",
        "84": "7500",
        "85": "7650",
        "86": "7800",
        "87": "8000",
        "88": "8200",
        "89": "8400",
        "90": "8600",
        "91": "9100",
        "92": "9600",
        "93": "10100",
        "94": "10600",
        "95": "11100",
        "96": "12100",
        "97": "13100",
        "98": "14100",
        "99": "15100",
        "100": "16100"
    },
    "user": {
        "536506865883021323": {
            "level": 24,
            "exp": 944
        },
        "642320951987535893": {
            "level": 12,
            "exp": 259
        },
        "159985870458322944": {
            "level": 18,
            "exp": 558
        },
        "693021919993266236": {
            "level": 7,
            "exp": 93
        },
        "598410545053564939": {
            "level": 5,
            "exp": 64
        },
        "634797595339915264": {
            "level": 9,
            "exp": 176
        },
        "686221386318217293": {
            "level": 12,
            "exp": 275
        },
        "552851796100513802": {
            "level": 7,
            "exp": 104
        },
        "641591300252237836": {
            "level": 4,
            "exp": 43
        },
        "537031688610512896": {
            "level": 13,
            "exp": 304
        },
        "505357370306592788": {
            "level": 1,
            "exp": 10
        },
        "302050872383242240": {
            "level": "0",
            "exp": "1"
        },
        "602129473084588044": {
            "level": 1,
            "exp": 11
        },
        "627877467662581780": {
            "level": "0",
            "exp": 5
        },
        "437929251107373057": {
            "level": "0",
            "exp": 4
        },
        "612302546052317204": {
            "level": "0",
            "exp": 3
        },
        "598355101845028895": {
            "level": "0",
            "exp": 2
        },
        "534994298827964416": {
            "level": 4,
            "exp": 36
        },
        "596623715425583107": {
            "level": "0",
            "exp": "1"
        },
        "524171589676171264": {
            "level": "0",
            "exp": 4
        }
    },
    "guild": {
        "661140302823686154": {
            "channel_id": 694809827276357632,
            "message": "{user}\u3055\u3093\u304c\u30ec\u30d9\u30eb{level}\u306b\u306a\u308a\u307e\u3057\u305f\uff01\ud83c\udf89",
            "roles": {
                "12": 694879538324439064
            }
        },
        "607485645753155594": {
            "channel_id": 694820821838856242,
            "message": "{user}\u3055\u3093\u304c{level}\u306b\u306a\u308a\u307e\u3057\u305f",
            "roles": {}
        },
        "663035527724793896": {
            "channel_id": 710054090817929226,
            "message": "{user}\u3055\u3093\u304clevel {level}\u306b\u306a\u308a\u307e\u3057\u305f\u3001\u304f\u305f\u3070\u308a\u306a\u3055\u3044(\u6bba\u610f)",
            "roles": {}
        }
    }
}